base_automation/__init__.py
base_automation/allure_installation.py
base_automation/base.py
base_automation/report.py
base_automation/socket.py
base_automation/sql.py
base_automation/upload_artifact.py
base_automation/schema/__init__.py
base_automation/schema/schema.py
base_automation/socket_connections/__init__.py
base_automation/socket_connections/echo_client.py
base_automation/socket_connections/echo_server.py
base_automation/socket_connections/server_multi_connections.py
base_automation/sql_capabilities/__init__.py
base_automation/sql_capabilities/my_sql_server.py
base_automation/utilities/__init__.py
base_automation/utilities/shared_utilities.py
base_automation-0.0.8.dist-info/METADATA
base_automation-0.0.8.dist-info/WHEEL
base_automation-0.0.8.dist-info/top_level.txt
base_automation-0.0.8.dist-info/RECORD
